advpyneng_cli_course/__init__.py
advpyneng_cli_course/apyneng.py
advpyneng_cli_course/apyneng_docs.py
advpyneng_cli_course/exceptions.py
advpyneng_cli_course/utils.py
advpyneng_cli_course-1.1.dist-info/LICENSE
advpyneng_cli_course-1.1.dist-info/METADATA
advpyneng_cli_course-1.1.dist-info/WHEEL
advpyneng_cli_course-1.1.dist-info/entry_points.txt
advpyneng_cli_course-1.1.dist-info/top_level.txt
advpyneng_cli_course-1.1.dist-info/RECORD
