Metadata-Version: 2.1
Name: advpyneng-cli-course
Version: 1.1
Summary: CLI tool for running advpyneng tests
Home-page: https://github.com/natenka/advpyneng-cli-course
Author: Natasha Samoylenko
Author-email: "Natasha Samoylenko" <natasha.samoylenko@gmail.com>
License: MIT
Classifier: License :: OSI Approved :: MIT License
License-File: LICENSE
Requires-Dist: pytest-json-report (>=1.2)
Requires-Dist: click
Requires-Dist: pyyaml
Requires-Dist: pytest
Requires-Dist: pytest-clarity
Requires-Dist: PyGitHub
Requires-Dist: six
Requires-Dist: rich
Requires-Dist: jinja2
Requires-Dist: textfsm
